<StructureDefinition xmlns="http://hl7.org/fhir"><id value="GithubProblems-CareConnect-AllergyIntolerance-update" /><meta><versionId value="1" /><lastUpdated value="2016-08-03T17:16:59.34+03:00" /></meta><url value="http://hl7.org.uk/CareConnect-AllergyIntolerance" /><version value="1.0" /><name value="AllergyIntolerance-1" /><status value="draft" /><description value="CareConnect AllergyIntolerance profile" /><fhirVersion value="1.0.2" /><kind value="resource" /><constrainedType value="AllergyIntolerance" /><abstract value="false" /><base value="http://hl7.org/fhir/StructureDefinition/AllergyIntolerance" /><differential><element><path value="AllergyIntolerance" /><type><code value="AllergyIntoleranceee" /></type></element></differential></StructureDefinition>
